dynamix/__init__.py
dynamix/utils.py
dynamix/correlator/__init__.py
dynamix/correlator/common.py
dynamix/correlator/cuda.py
dynamix/correlator/dense.py
dynamix/correlator/event.py
dynamix/correlator/intensity.py
dynamix/correlator/test/__init__.py
dynamix/correlator/test/test_dense.py
dynamix/correlator/test/test_event.py
dynamix/resources/__init__.py
dynamix/resources/opencl/correlator.cl
dynamix/resources/opencl/densecorrelator.cl
dynamix/resources/opencl/evtcorrelator.cl
dynamix/test/__init__.py
dynamix/test/utils.py
dynamix-0.1.0.dist-info/LICENSE
dynamix-0.1.0.dist-info/METADATA
dynamix-0.1.0.dist-info/WHEEL
dynamix-0.1.0.dist-info/top_level.txt
dynamix-0.1.0.dist-info/zip-safe
dynamix-0.1.0.dist-info/RECORD
